pohan/__init__.py
pohan/api/__init__.py
pohan/api/common.py
pohan/api/普通话.py
pohan/api/重庆话.py
pohan/lib/__init__.py
pohan/pinyin/__init__.py
pohan/pinyin/pinyin.py
tests/__init__.py
tests/test_pohan.py
pohan-0.0.6.dist-info/LICENSE
pohan-0.0.6.dist-info/METADATA
pohan-0.0.6.dist-info/WHEEL
pohan-0.0.6.dist-info/top_level.txt
pohan-0.0.6.dist-info/RECORD
