Metadata-Version: 2.1
Name: pohan
Version: 0.0.6
Summary: pip install pohan
Home-page: https://www.python-office.com/
Author: CoderWanFeng
Author-email: 1957875073@qq.com
License: MIT
Project-URL: Bug Tracker, https://github.com/CoderWanFeng/pohan/issues
Project-URL: Documentation, https://github.com/CoderWanFeng/pohan/blob/master/README.md
Project-URL: Source Code, https://github.com/CoderWanFeng/pohan
Platform: any
Requires-Python: >=3.6
License-File: LICENSE
Requires-Dist: pypinyin
